Metadata-Version: 2.1
Name: mvcpy
Version: 0.0.1
Summary: molecularclustering
Author: Abdulsalam Raja
Classifier: Programming Language :: Python :: 3
Classifier: License :: OSI Approved :: MIT License
Classifier: Operating System :: OS Independent
Requires-Python: >=3.7
License-File: LICENSE.txt
